alexeygameframework/__init__.py
alexeygameframework/testing2.py
alexeygameframework/Utilities/UIElements.py
alexeygameframework/Utilities/__init__.py
alexeygameframework/Utilities/gameInfo.py
alexeygameframework/Utilities/gameState.py
alexeygameframework/Utilities/objects.py
alexeygameframework/Utilities/tilemap.py
alexeygameframework/Utilities/utils.py
alexeygameframework-0.0.13.dist-info/LICENCE.txt
alexeygameframework-0.0.13.dist-info/METADATA
alexeygameframework-0.0.13.dist-info/WHEEL
alexeygameframework-0.0.13.dist-info/top_level.txt
alexeygameframework-0.0.13.dist-info/RECORD
