Metadata-Version: 2.1
Name: alexeygameframework
Version: 0.0.13
Summary: A simple game framework designed with pygame
Home-page: 
Author: Alexey Kazinich
Author-email: 
License: MIT
Keywords: game
Classifier: Development Status :: 4 - Beta
Classifier: Intended Audience :: Education
Classifier: Operating System :: Microsoft :: Windows :: Windows 10
Classifier: License :: OSI Approved :: MIT License
Classifier: Programming Language :: Python :: 3
License-File: LICENCE.txt
Requires-Dist: pygame
